[
  {
    "id": "cmhjflyo900022f5w1lep7dqu",
    "programacao_id": "cmhjflxy200012f5w6zogbbww",
    "descricao": "teste material 1",
    "quantidade_planejada": "1",
    "unidade": "UN",
    "custo_unitario": "299.98",
    "custo_total": "299.98",
    "confirmado": false,
    "disponivel": true,
    "observacoes": null,
    "created_at": "2025-11-03T17:46:26.122Z",
    "updated_at": "2025-11-03T17:46:26.122Z"
  },
  {
    "id": "cmhti4wg300022focii3vilwh",
    "programacao_id": "cmhti4vse00012foc9c9cr0an",
    "descricao": "feafeafeafae",
    "quantidade_planejada": "1",
    "unidade": "UN",
    "custo_unitario": "9",
    "custo_total": "9",
    "confirmado": false,
    "disponivel": true,
    "observacoes": null,
    "created_at": "2025-11-10T18:54:50.691Z",
    "updated_at": "2025-11-10T18:54:50.691Z"
  },
  {
    "id": "cmhtispeo000q2f0g0xozsdsl",
    "programacao_id": "cmhtisoo2000p2f0gpwz272xi",
    "descricao": "aaaaaaaaaa",
    "quantidade_planejada": "5",
    "unidade": "UN",
    "custo_unitario": "2.97",
    "custo_total": "14.85",
    "confirmado": false,
    "disponivel": true,
    "observacoes": null,
    "created_at": "2025-11-10T19:13:21.313Z",
    "updated_at": "2025-11-10T19:13:21.313Z"
  },
  {
    "id": "cmj0iftv600182fr0yru4rlm2",
    "programacao_id": "cmj0ifrnm00152fr0str3aahm",
    "descricao": "teste",
    "quantidade_planejada": "1",
    "unidade": "UN",
    "custo_unitario": "70",
    "custo_total": "70",
    "confirmado": false,
    "disponivel": true,
    "observacoes": null,
    "created_at": "2025-12-10T21:17:26.129Z",
    "updated_at": "2025-12-10T21:17:26.129Z"
  },
  {
    "id": "cmj0iftv600192fr0m6qaomst",
    "programacao_id": "cmj0ifrnm00152fr0str3aahm",
    "descricao": "teste 2",
    "quantidade_planejada": "1",
    "unidade": "UN",
    "custo_unitario": "6",
    "custo_total": "6",
    "confirmado": false,
    "disponivel": true,
    "observacoes": null,
    "created_at": "2025-12-10T21:17:26.129Z",
    "updated_at": "2025-12-10T21:17:26.129Z"
  }
]